README.md
setup.py
resultsdb_updater.egg-info/PKG-INFO
resultsdb_updater.egg-info/SOURCES.txt
resultsdb_updater.egg-info/dependency_links.txt
resultsdb_updater.egg-info/entry_points.txt
resultsdb_updater.egg-info/requires.txt
resultsdb_updater.egg-info/top_level.txt
resultsdbupdater/__init__.py
resultsdbupdater/consumer.py
resultsdbupdater/utils.py
tests/__init__.py
tests/test_consumer.py
tests/test_utils.py