Metadata-Version: 1.0
Name: resultsdb-updater
Version: 5.3.0
Summary: A micro-service that listens for messages on the message bus and updates ResultsDB
Home-page: https://github.com/release-engineering/resultsdb-updater
Author: Matt Prahl
Author-email: mprahl@redhat.com
License: GPLv2+
Platform: UNKNOWN
